contract/__init__.py
contract/contract.py
loxtest/__init__.py
loxtest/cli.py
loxtest/plugin.py
loxygen/__init__.py
loxygen/environment.py
loxygen/exceptions.py
loxygen/interpreter.py
loxygen/loxygen.py
loxygen/nodes.py
loxygen/parser.py
loxygen/resolver.py
loxygen/runtime.py
loxygen/scanner.py
loxygen/token.py
loxygen-0.2.0.dist-info/licenses/LICENSE
loxygen-0.2.0.dist-info/METADATA
loxygen-0.2.0.dist-info/WHEEL
loxygen-0.2.0.dist-info/entry_points.txt
loxygen-0.2.0.dist-info/top_level.txt
loxygen-0.2.0.dist-info/RECORD
