Metadata-Version: 2.4
Name: loxygen
Version: 0.2.0
Summary: A Lox interpreter in Python and a pytest plugin for testing Lox interpreters.
License-Expression: MIT
Requires-Python: >=3.12
License-File: LICENSE
Requires-Dist: pytest>=8.3
Provides-Extra: dev
Requires-Dist: mypy>=1.17; extra == "dev"
Requires-Dist: pre-commit>=3.8; extra == "dev"
Requires-Dist: ruff>=0.12; extra == "dev"
Dynamic: license-file
